web_compile/__init__.py
web_compile/config.py
web_compile-0.2.3.dist-info/LICENSE
web_compile-0.2.3.dist-info/METADATA
web_compile-0.2.3.dist-info/WHEEL
web_compile-0.2.3.dist-info/entry_points.txt
web_compile-0.2.3.dist-info/top_level.txt
web_compile-0.2.3.dist-info/RECORD
