Metadata-Version: 2.1
Name: web-compile
Version: 0.2.3
Summary: A CLI to compile/minify SCSS & JS, and associated pre-commit hook.
Home-page: https://github.com/executablebooks/web-compile
Author: Chris Sewell
Author-email: chrisj_sewell@hotmail.com
License: MIT
Keywords: sass scss js jinja compile pre-commit
Platform: UNKNOWN
Classifier: License :: OSI Approved :: MIT License
Classifier: Programming Language :: Python :: 3
Requires-Python: >=3.6
Requires-Dist: click (<10.0.0,>=7.1.2)
Requires-Dist: jinja2 (~=3.0.3)
Requires-Dist: libsass (~=0.20.1)
Requires-Dist: gitpython (~=3.1.8)
Requires-Dist: pyyaml
Requires-Dist: rjsmin (~=1.1.0)
Requires-Dist: toml
Provides-Extra: testing
Requires-Dist: pytest (~=6.0.1) ; extra == 'testing'
